indigo/__init__.py
indigo/_common/__init__.py
indigo/_common/lib.py
indigo/bingo/__init__.py
indigo/bingo/bingo.py
indigo/bingo/bingo_exception.py
indigo/bingo/bingo_lib.py
indigo/bingo/bingo_object.py
indigo/inchi/__init__.py
indigo/inchi/inchi.py
indigo/inchi/indigo_inchi_lib.py
indigo/indigo/__init__.py
indigo/indigo/hybridization.py
indigo/indigo/indigo.py
indigo/indigo/indigo_exception.py
indigo/indigo/indigo_lib.py
indigo/indigo/indigo_object.py
indigo/indigo/salts.py
indigo/lib/darwin-x86_64/libbingo-nosql.dylib
indigo/lib/darwin-x86_64/libindigo-inchi.dylib
indigo/lib/darwin-x86_64/libindigo-renderer.dylib
indigo/lib/darwin-x86_64/libindigo.dylib
indigo/renderer/__init__.py
indigo/renderer/indigo_renderer_lib.py
indigo/renderer/renderer.py
epam_indigo-1.36.1.dist-info/METADATA
epam_indigo-1.36.1.dist-info/WHEEL
epam_indigo-1.36.1.dist-info/top_level.txt
epam_indigo-1.36.1.dist-info/RECORD
