Metadata-Version: 2.1
Name: epam-indigo
Version: 1.36.1
Summary: Indigo universal cheminformatics toolkit
Home-page: https://lifescience.opensource.epam.com/indigo/index.html
Download-URL: https://pypi.org/project/epam.indigo
Author: EPAM Systems Life Science Department
Author-email: lifescience.opensource@epam.com
Maintainer: Lifescience Opensource
Maintainer-email: lifescience.opensource@epam.com
License: Apache-2.0
Project-URL: Bug Tracker, https://github.com/epam/indigo/issues
Project-URL: Documentation, https://lifescience.opensource.epam.com/indigo/api/index.html
Project-URL: Source Code, https://github.com/epam/indigo/
Platform: Windows
Platform: Linux
Platform: Mac OS-X
Classifier: Development Status :: 5 - Production/Stable
Classifier: Intended Audience :: Science/Research
Classifier: Intended Audience :: Developers
Classifier: License :: OSI Approved :: Apache Software License
Classifier: Programming Language :: C
Classifier: Programming Language :: C++
Classifier: Programming Language :: Python
Classifier: Programming Language :: Python :: 3
Classifier: Programming Language :: Python :: 3.6
Classifier: Programming Language :: Python :: 3.7
Classifier: Programming Language :: Python :: 3.8
Classifier: Programming Language :: Python :: 3.9
Classifier: Programming Language :: Python :: 3.10
Classifier: Programming Language :: Python :: Implementation :: CPython
Classifier: Topic :: Software Development
Classifier: Topic :: Scientific/Engineering :: Chemistry
Classifier: Operating System :: Microsoft :: Windows
Classifier: Operating System :: POSIX :: Linux
Classifier: Operating System :: MacOS
Requires-Python: >=3.6.0
